{
  "model": "MES Futures v11.0 \u2014 ML Scoring (OR breakout, 22 features)",
  "period": "2023-03-27 to 2026-05-28",
  "product": "MES $5/pt",
  "strategy": "WalkForward LightGBM \u00b7 P(win)\u22650.52 \u00b7 OR breakout \u00b7 ATR SL \u00b7 10:30 PRIME",
  "total_trades": 159,
  "prime_trades": 159,
  "wins": 76,
  "losses": 83,
  "win_rate": 0.478,
  "profit_factor": 1.4729,
  "rr_ratio": 1.6086,
  "annual_return": 19.4,
  "max_drawdown": 0.1281,
  "sharpe_ratio": 2.3733,
  "sortino_ratio": 4.7374,
  "calmar_ratio": 1.5147,
  "start_balance": 10000.0,
  "end_balance": 17544.11,
  "total_pnl": 7544.11,
  "pnl_pct": 75.44,
  "years": 3.1704,
  "yearly_pnl": {
    "2023": 598.46,
    "2024": 2513.05,
    "2025": 3476.06,
    "2026": 956.54
  },
  "feature_importance": {
    "prev_range": 0.1587,
    "mom_30m": 0.1151,
    "rsi_norm": 0.1151,
    "gap_norm": 0.1071,
    "mom_5m": 0.0675,
    "mom_day": 0.0635,
    "prev_close_pos": 0.0635,
    "month_norm": 0.0556,
    "mom_15m": 0.0397,
    "streak_norm": 0.0397,
    "or_width_norm": 0.0357,
    "vwap_dist": 0.0317,
    "ema_dist": 0.0278,
    "vol_ratio": 0.0198,
    "dow_norm": 0.0198,
    "recent_wr5": 0.0198,
    "atr_expand": 0.0159,
    "or_position": 0.004,
    "or_breakout": 0.0,
    "atr_norm": 0.0,
    "direction": 0.0,
    "atr_regime": 0.0
  },
  "ml_stats": {
    "warmup_trades": 25,
    "ml_filtered": 636,
    "ml_passed": 134
  },
  "trades": [
    {
      "date": "2023-03-28",
      "direction": "LONG",
      "entry_price": 4000.75,
      "exit_price": 3988.75,
      "exit_type": "EOD",
      "sl_points": 22.0,
      "atr": 29.5,
      "contracts": 2,
      "pnl": -122.48,
      "balance": 9877.52,
      "ml_confidence": 0.5,
      "ml_active": false,
      "or_breakout": 0.0,
      "mom_30m": 0.1186
    },
    {
      "date": "2023-03-29",
      "direction": "SHORT",
      "entry_price": 4040.0,
      "exit_price": 4056.0,
      "exit_type": "EOD",
      "sl_points": 22.0,
      "atr": 45.0,
      "contracts": 2,
      "pnl": -162.48,
      "balance": 9715.04,
      "ml_confidence": 0.5,
      "ml_active": false,
      "or_breakout": 0.0,
      "mom_30m": -0.0778
    },
    {
      "date": "2023-03-30",
      "direction": "SHORT",
      "entry_price": 4083.0,
      "exit_price": 4071.4375,
      "exit_type": "SL",
      "sl_points": 22.0,
      "atr": 39.75,
      "contracts": 2,
      "pnl": 113.14,
      "balance": 9828.19,
      "ml_confidence": 0.5,
      "ml_active": false,
      "or_breakout": 0.0,
      "mom_30m": -0.0566
    },
    {
      "date": "2023-03-31",
      "direction": "SHORT",
      "entry_price": 4102.0,
      "exit_price": 4124.25,
      "exit_type": "SL",
      "sl_points": 22.0,
      "atr": 45.0,
      "contracts": 2,
      "pnl": -224.98,
      "balance": 9603.21,
      "ml_confidence": 0.5,
      "ml_active": false,
      "or_breakout": 0.0,
      "mom_30m": 0.0
    },
    {
      "date": "2023-04-03",
      "direction": "LONG",
      "entry_price": 4154.5,
      "exit_price": 4132.25,
      "exit_type": "SL",
      "sl_points": 22.0,
      "atr": 42.0,
      "contracts": 2,
      "pnl": -224.98,
      "balance": 9378.23,
      "ml_confidence": 0.5,
      "ml_active": false,
      "or_breakout": 1.0,
      "mom_30m": 0.125
    },
    {
      "date": "2023-04-04",
      "direction": "SHORT",
      "entry_price": 4149.0,
      "exit_price": 4126.25,
      "exit_type": "SL",
      "sl_points": 22.0,
      "atr": 43.0,
      "contracts": 2,
      "pnl": 225.02,
      "balance": 9603.25,
      "ml_confidence": 0.5,
      "ml_active": false,
      "or_breakout": 0.0,
      "mom_30m": -0.2965
    },
    {
      "date": "2023-04-05",
      "direction": "SHORT",
      "entry_price": 4114.5,
      "exit_price": 4114.75,
      "exit_type": "SL",
      "sl_points": 22.0,
      "atr": 41.2857,
      "contracts": 2,
      "pnl": -4.98,
      "balance": 9598.27,
      "ml_confidence": 0.5,
      "ml_active": false,
      "or_breakout": -1.0,
      "mom_30m": -0.2483
    },
    {
      "date": "2023-04-06",
      "direction": "LONG",
      "entry_price": 4109.0,
      "exit_price": 4130.0,
      "exit_type": "EOD",
      "sl_points": 22.0,
      "atr": 41.0,
      "contracts": 2,
      "pnl": 207.52,
      "balance": 9805.79,
      "ml_confidence": 0.5,
      "ml_active": false,
      "or_breakout": 0.0,
      "mom_30m": 0.128
    },
    {
      "date": "2023-04-10",
      "direction": "LONG",
      "entry_price": 4106.5,
      "exit_price": 4106.25,
      "exit_type": "SL",
      "sl_points": 22.0,
      "atr": 40.7778,
      "contracts": 2,
      "pnl": -4.98,
      "balance": 9800.81,
      "ml_confidence": 0.5,
      "ml_active": false,
      "or_breakout": 0.0,
      "mom_30m": 0.1349
    },
    {
      "date": "2023-04-11",
      "direction": "LONG",
      "entry_price": 4139.75,
      "exit_price": 4150.25,
      "exit_type": "EOD",
      "sl_points": 22.0,
      "atr": 39.0,
      "contracts": 2,
      "pnl": 102.52,
      "balance": 9903.33,
      "ml_confidence": 0.5,
      "ml_active": false,
      "or_breakout": 0.0,
      "mom_30m": 0.1154
    },
    {
      "date": "2023-04-12",
      "direction": "LONG",
      "entry_price": 4151.25,
      "exit_price": 4129.0,
      "exit_type": "SL",
      "sl_points": 22.0,
      "atr": 39.7727,
      "contracts": 2,
      "pnl": -224.98,
      "balance": 9678.35,
      "ml_confidence": 0.5,
      "ml_active": false,
      "or_breakout": 0.0,
      "mom_30m": 0.1949
    },
    {
      "date": "2023-04-13",
      "direction": "LONG",
      "entry_price": 4145.25,
      "exit_price": 4172.75,
      "exit_type": "EOD",
      "sl_points": 22.0,
      "atr": 41.1667,
      "contracts": 2,
      "pnl": 272.52,
      "balance": 9950.87,
      "ml_confidence": 0.5,
      "ml_active": false,
      "or_breakout": 1.0,
      "mom_30m": 0.3644
    },
    {
      "date": "2023-04-14",
      "direction": "SHORT",
      "entry_price": 4163.25,
      "exit_price": 4149.2356,
      "exit_type": "SL",
      "sl_points": 22.0,
      "atr": 41.9423,
      "contracts": 2,
      "pnl": 137.66,
      "balance": 10088.53,
      "ml_confidence": 0.5,
      "ml_active": false,
      "or_breakout": -1.0,
      "mom_30m": -0.4053
    },
    {
      "date": "2023-04-17",
      "direction": "SHORT",
      "entry_price": 4165.0,
      "exit_price": 4165.25,
      "exit_type": "SL",
      "sl_points": 22.0,
      "atr": 41.0893,
      "contracts": 2,
      "pnl": -4.98,
      "balance": 10083.55,
      "ml_confidence": 0.5,
      "ml_active": false,
      "or_breakout": 0.0,
      "mom_30m": -0.0487
    },
    {
      "date": "2023-04-18",
      "direction": "SHORT",
      "entry_price": 4167.25,
      "exit_price": 4176.75,
      "exit_type": "EOD",
      "sl_points": 22.0,
      "atr": 41.1429,
      "contracts": 2,
      "pnl": -97.48,
      "balance": 9986.07,
      "ml_confidence": 0.5,
      "ml_active": false,
      "or_breakout": -1.0,
      "mom_30m": -0.395
    },
    {
      "date": "2023-04-19",
      "direction": "LONG",
      "entry_price": 4165.0,
      "exit_price": 4177.5134,
      "exit_type": "SL",
      "sl_points": 22.0,
      "atr": 38.9464,
      "contracts": 2,
      "pnl": 122.65,
      "balance": 10108.72,
      "ml_confidence": 0.624,
      "ml_active": false,
      "or_breakout": 1.0,
      "mom_30m": 0.122
    },
    {
      "date": "2023-04-20",
      "direction": "LONG",
      "entry_price": 4157.5,
      "exit_price": 4157.25,
      "exit_type": "SL",
      "sl_points": 22.0,
      "atr": 39.8393,
      "contracts": 2,
      "pnl": -4.98,
      "balance": 10103.74,
      "ml_confidence": 0.3282,
      "ml_active": false,
      "or_breakout": 0.0,
      "mom_30m": 0.182
    },
    {
      "date": "2023-04-21",
      "direction": "LONG",
      "entry_price": 4154.0,
      "exit_price": 4151.75,
      "exit_type": "EOD",
      "sl_points": 22.0,
      "atr": 37.3393,
      "contracts": 2,
      "pnl": -24.98,
      "balance": 10078.76,
      "ml_confidence": 0.3893,
      "ml_active": false,
      "or_breakout": 0.0,
      "mom_30m": 0.2946
    },
    {
      "date": "2023-04-24",
      "direction": "LONG",
      "entry_price": 4163.25,
      "exit_price": 4141.0,
      "exit_type": "SL",
      "sl_points": 22.0,
      "atr": 37.0536,
      "contracts": 2,
      "pnl": -224.98,
      "balance": 9853.78,
      "ml_confidence": 0.624,
      "ml_active": false,
      "or_breakout": 0.0,
      "mom_30m": 0.0742
    },
    {
      "date": "2023-04-26",
      "direction": "SHORT",
      "entry_price": 4086.25,
      "exit_price": 4108.5,
      "exit_type": "SL",
      "sl_points": 22.0,
      "atr": 39.5357,
      "contracts": 2,
      "pnl": -224.98,
      "balance": 9628.8,
      "ml_confidence": 0.624,
      "ml_active": false,
      "or_breakout": -1.0,
      "mom_30m": -0.3162
    },
    {
      "date": "2023-04-27",
      "direction": "LONG",
      "entry_price": 4112.75,
      "exit_price": 4152.75,
      "exit_type": "EOD",
      "sl_points": 22.0,
      "atr": 42.6786,
      "contracts": 2,
      "pnl": 397.52,
      "balance": 10026.32,
      "ml_confidence": 0.6892,
      "ml_active": false,
      "or_breakout": 1.0,
      "mom_30m": 0.1523
    },
    {
      "date": "2023-04-28",
      "direction": "LONG",
      "entry_price": 4177.75,
      "exit_price": 4155.5,
      "exit_type": "SL",
      "sl_points": 22.0,
      "atr": 43.1964,
      "contracts": 2,
      "pnl": -224.98,
      "balance": 9801.34,
      "ml_confidence": 0.7061,
      "ml_active": false,
      "or_breakout": 1.0,
      "mom_30m": 0.5209
    },
    {
      "date": "2023-05-01",
      "direction": "SHORT",
      "entry_price": 4190.25,
      "exit_price": 4189.0,
      "exit_type": "EOD",
      "sl_points": 22.0,
      "atr": 43.2857,
      "contracts": 2,
      "pnl": 10.02,
      "balance": 9811.36,
      "ml_confidence": 0.6644,
      "ml_active": false,
      "or_breakout": 0.0,
      "mom_30m": -0.0231
    },
    {
      "date": "2023-05-02",
      "direction": "SHORT",
      "entry_price": 4134.5,
      "exit_price": 4117.1384,
      "exit_type": "SL",
      "sl_points": 22.0,
      "atr": 45.5536,
      "contracts": 2,
      "pnl": 171.14,
      "balance": 9982.5,
      "ml_confidence": 0.2007,
      "ml_active": false,
      "or_breakout": -1.0,
      "mom_30m": -0.7134
    },
    {
      "date": "2023-05-03",
      "direction": "SHORT",
      "entry_price": 4142.75,
      "exit_price": 4143.0,
      "exit_type": "SL",
      "sl_points": 22.0,
      "atr": 45.9464,
      "contracts": 2,
      "pnl": -4.98,
      "balance": 9977.52,
      "ml_confidence": 0.1675,
      "ml_active": true,
      "or_breakout": 0.0,
      "mom_30m": -0.2068
    },
    {
      "date": "2023-05-05",
      "direction": "LONG",
      "entry_price": 4135.0,
      "exit_price": 4157.25,
      "exit_type": "EOD",
      "sl_points": 22.0,
      "atr": 49.5179,
      "contracts": 3,
      "pnl": 330.03,
      "balance": 10307.55,
      "ml_confidence": 0.64,
      "ml_active": true,
      "or_breakout": 1.0,
      "mom_30m": 0.1161
    },
    {
      "date": "2023-05-18",
      "direction": "LONG",
      "entry_price": 4189.5,
      "exit_price": 4196.25,
      "exit_type": "EOD",
      "sl_points": 22.0,
      "atr": 45.9643,
      "contracts": 2,
      "pnl": 65.02,
      "balance": 10372.57,
      "ml_confidence": 0.571,
      "ml_active": true,
      "or_breakout": 1.0,
      "mom_30m": 0.4514
    },
    {
      "date": "2023-05-25",
      "direction": "SHORT",
      "entry_price": 4143.75,
      "exit_price": 4166.0,
      "exit_type": "SL",
      "sl_points": 22.0,
      "atr": 39.8036,
      "contracts": 3,
      "pnl": -337.47,
      "balance": 10035.1,
      "ml_confidence": 0.6667,
      "ml_active": true,
      "or_breakout": 0.0,
      "mom_30m": -0.1507
    },
    {
      "date": "2023-05-26",
      "direction": "LONG",
      "entry_price": 4206.0,
      "exit_price": 4214.25,
      "exit_type": "EOD",
      "sl_points": 22.0,
      "atr": 42.75,
      "contracts": 3,
      "pnl": 120.03,
      "balance": 10155.13,
      "ml_confidence": 0.7422,
      "ml_active": true,
      "or_breakout": 1.0,
      "mom_30m": 0.386
    },
    {
      "date": "2023-06-02",
      "direction": "LONG",
      "entry_price": 4265.5,
      "exit_price": 4290.25,
      "exit_type": "EOD",
      "sl_points": 22.0,
      "atr": 45.1607,
      "contracts": 2,
      "pnl": 245.02,
      "balance": 10400.15,
      "ml_confidence": 0.5865,
      "ml_active": true,
      "or_breakout": 0.0,
      "mom_30m": 0.2546
    },
    {
      "date": "2023-06-08",
      "direction": "LONG",
      "entry_price": 4282.0,
      "exit_price": 4295.5,
      "exit_type": "EOD",
      "sl_points": 22.0,
      "atr": 42.5,
      "contracts": 3,
      "pnl": 198.78,
      "balance": 10598.93,
      "ml_confidence": 0.7289,
      "ml_active": true,
      "or_breakout": 1.0,
      "mom_30m": 0.2647
    },
    {
      "date": "2023-06-09",
      "direction": "LONG",
      "entry_price": 4325.0,
      "exit_price": 4302.75,
      "exit_type": "SL",
      "sl_points": 22.0,
      "atr": 42.5536,
      "contracts": 3,
      "pnl": -337.47,
      "balance": 10261.46,
      "ml_confidence": 0.7615,
      "ml_active": true,
      "or_breakout": 1.0,
      "mom_30m": 0.1762
    },
    {
      "date": "2023-06-13",
      "direction": "LONG",
      "entry_price": 4361.25,
      "exit_price": 4361.0,
      "exit_type": "SL",
      "sl_points": 22.0,
      "atr": 40.9286,
      "contracts": 3,
      "pnl": -7.47,
      "balance": 10253.99,
      "ml_confidence": 0.7713,
      "ml_active": true,
      "or_breakout": 0.0,
      "mom_30m": 0.0305
    },
    {
      "date": "2023-06-15",
      "direction": "LONG",
      "entry_price": 4394.75,
      "exit_price": 4430.1205,
      "exit_type": "SL",
      "sl_points": 22.0,
      "atr": 42.5179,
      "contracts": 3,
      "pnl": 526.84,
      "balance": 10780.83,
      "ml_confidence": 0.728,
      "ml_active": true,
      "or_breakout": 1.0,
      "mom_30m": 0.1764
    },
    {
      "date": "2023-06-21",
      "direction": "LONG",
      "entry_price": 4415.75,
      "exit_price": 4416.75,
      "exit_type": "EOD",
      "sl_points": 22.0,
      "atr": 42.1964,
      "contracts": 3,
      "pnl": 11.28,
      "balance": 10792.11,
      "ml_confidence": 0.7501,
      "ml_active": true,
      "or_breakout": 0.0,
      "mom_30m": 0.1363
    },
    {
      "date": "2023-06-22",
      "direction": "LONG",
      "entry_price": 4413.25,
      "exit_price": 4413.0,
      "exit_type": "SL",
      "sl_points": 22.0,
      "atr": 39.9821,
      "contracts": 2,
      "pnl": -4.98,
      "balance": 10787.13,
      "ml_confidence": 0.5867,
      "ml_active": true,
      "or_breakout": 1.0,
      "mom_30m": 0.1563
    },
    {
      "date": "2023-06-23",
      "direction": "LONG",
      "entry_price": 4396.5,
      "exit_price": 4396.25,
      "exit_type": "SL",
      "sl_points": 22.0,
      "atr": 38.0357,
      "contracts": 3,
      "pnl": -7.47,
      "balance": 10779.66,
      "ml_confidence": 0.7765,
      "ml_active": true,
      "or_breakout": 1.0,
      "mom_30m": 0.1315
    },
    {
      "date": "2023-06-27",
      "direction": "LONG",
      "entry_price": 4385.0,
      "exit_price": 4423.0,
      "exit_type": "EOD",
      "sl_points": 22.0,
      "atr": 40.1429,
      "contracts": 3,
      "pnl": 566.28,
      "balance": 11345.94,
      "ml_confidence": 0.8044,
      "ml_active": true,
      "or_breakout": 0.0,
      "mom_30m": 0.0311
    },
    {
      "date": "2023-06-28",
      "direction": "LONG",
      "entry_price": 4412.25,
      "exit_price": 4412.0,
      "exit_type": "SL",
      "sl_points": 22.0,
      "atr": 39.8214,
      "contracts": 4,
      "pnl": -9.96,
      "balance": 11335.98,
      "ml_confidence": 0.864,
      "ml_active": true,
      "or_breakout": 1.0,
      "mom_30m": 0.1632
    },
    {
      "date": "2023-06-29",
      "direction": "SHORT",
      "entry_price": 4418.0,
      "exit_price": 4430.75,
      "exit_type": "EOD",
      "sl_points": 22.0,
      "atr": 39.1071,
      "contracts": 3,
      "pnl": -194.97,
      "balance": 11141.01,
      "ml_confidence": 0.6006,
      "ml_active": true,
      "or_breakout": 0.0,
      "mom_30m": -0.1023
    },
    {
      "date": "2023-07-03",
      "direction": "SHORT",
      "entry_price": 4488.0,
      "exit_price": 4492.0,
      "exit_type": "END",
      "sl_points": 22.0,
      "atr": 39.5179,
      "contracts": 4,
      "pnl": -84.96,
      "balance": 11056.05,
      "ml_confidence": 0.7568,
      "ml_active": true,
      "or_breakout": 0.0,
      "mom_30m": -0.019
    },
    {
      "date": "2023-07-12",
      "direction": "LONG",
      "entry_price": 4521.75,
      "exit_price": 4499.5,
      "exit_type": "SL",
      "sl_points": 22.0,
      "atr": 36.2857,
      "contracts": 4,
      "pnl": -449.96,
      "balance": 10606.09,
      "ml_confidence": 0.7042,
      "ml_active": true,
      "or_breakout": 1.0,
      "mom_30m": 0.1654
    },
    {
      "date": "2023-07-28",
      "direction": "LONG",
      "entry_price": 4604.5,
      "exit_price": 4604.25,
      "exit_type": "SL",
      "sl_points": 22.0,
      "atr": 39.125,
      "contracts": 3,
      "pnl": -7.47,
      "balance": 10598.62,
      "ml_confidence": 0.6874,
      "ml_active": true,
      "or_breakout": 0.0,
      "mom_30m": 0.1022
    },
    {
      "date": "2023-07-31",
      "direction": "LONG",
      "entry_price": 4614.5,
      "exit_price": 4605.0,
      "exit_type": "EOD",
      "sl_points": 22.0,
      "atr": 38.0536,
      "contracts": 3,
      "pnl": -146.22,
      "balance": 10452.4,
      "ml_confidence": 0.6966,
      "ml_active": true,
      "or_breakout": 0.0,
      "mom_30m": 0.2496
    },
    {
      "date": "2023-08-04",
      "direction": "LONG",
      "entry_price": 4537.25,
      "exit_price": 4550.1071,
      "exit_type": "SL",
      "sl_points": 22.0,
      "atr": 41.5714,
      "contracts": 3,
      "pnl": 189.14,
      "balance": 10641.53,
      "ml_confidence": 0.7425,
      "ml_active": true,
      "or_breakout": 0.0,
      "mom_30m": 0.0782
    },
    {
      "date": "2023-08-10",
      "direction": "SHORT",
      "entry_price": 4538.75,
      "exit_price": 4526.3348,
      "exit_type": "SL",
      "sl_points": 22.0,
      "atr": 47.3393,
      "contracts": 2,
      "pnl": 121.67,
      "balance": 10763.21,
      "ml_confidence": 0.5724,
      "ml_active": true,
      "or_breakout": 0.0,
      "mom_30m": -0.0581
    },
    {
      "date": "2023-08-11",
      "direction": "LONG",
      "entry_price": 4487.25,
      "exit_price": 4484.0,
      "exit_type": "EOD",
      "sl_points": 22.0,
      "atr": 47.7321,
      "contracts": 3,
      "pnl": -52.47,
      "balance": 10710.74,
      "ml_confidence": 0.6268,
      "ml_active": true,
      "or_breakout": 1.0,
      "mom_30m": 0.2776
    },
    {
      "date": "2023-08-31",
      "direction": "LONG",
      "entry_price": 4538.0,
      "exit_price": 4515.75,
      "exit_type": "SL",
      "sl_points": 22.0,
      "atr": 50.0714,
      "contracts": 2,
      "pnl": -224.98,
      "balance": 10485.76,
      "ml_confidence": 0.5667,
      "ml_active": true,
      "or_breakout": 1.0,
      "mom_30m": 0.0549
    },
    {
      "date": "2023-09-08",
      "direction": "LONG",
      "entry_price": 4477.0,
      "exit_price": 4454.75,
      "exit_type": "SL",
      "sl_points": 22.0,
      "atr": 42.4643,
      "contracts": 2,
      "pnl": -224.98,
      "balance": 10260.78,
      "ml_confidence": 0.5896,
      "ml_active": true,
      "or_breakout": 1.0,
      "mom_30m": 0.2649
    },
    {
      "date": "2023-09-13",
      "direction": "SHORT",
      "entry_price": 4467.25,
      "exit_price": 4465.75,
      "exit_type": "EOD",
      "sl_points": 22.0,
      "atr": 36.2321,
      "contracts": 3,
      "pnl": 18.78,
      "balance": 10279.56,
      "ml_confidence": 0.6233,
      "ml_active": true,
      "or_breakout": 0.0,
      "mom_30m": -0.1035
    },
    {
      "date": "2023-09-14",
      "direction": "SHORT",
      "entry_price": 4487.75,
      "exit_price": 4510.0,
      "exit_type": "SL",
      "sl_points": 22.0,
      "atr": 34.8036,
      "contracts": 2,
      "pnl": -224.98,
      "balance": 10054.58,
      "ml_confidence": 0.5364,
      "ml_active": true,
      "or_breakout": 0.0,
      "mom_30m": -0.0575
    },
    {
      "date": "2023-09-22",
      "direction": "LONG",
      "entry_price": 4388.0,
      "exit_price": 4387.75,
      "exit_type": "SL",
      "sl_points": 22.0,
      "atr": 37.8393,
      "contracts": 2,
      "pnl": -4.98,
      "balance": 10049.6,
      "ml_confidence": 0.587,
      "ml_active": true,
      "or_breakout": 1.0,
      "mom_30m": 0.2048
    },
    {
      "date": "2023-10-06",
      "direction": "LONG",
      "entry_price": 4280.75,
      "exit_price": 4335.5,
      "exit_type": "TP",
      "sl_points": 22.0,
      "atr": 58.2857,
      "contracts": 2,
      "pnl": 545.02,
      "balance": 10594.62,
      "ml_confidence": 0.5321,
      "ml_active": true,
      "or_breakout": 1.0,
      "mom_30m": 0.3045
    },
    {
      "date": "2023-10-16",
      "direction": "LONG",
      "entry_price": 4406.0,
      "exit_price": 4409.5,
      "exit_type": "EOD",
      "sl_points": 22.0,
      "atr": 58.1429,
      "contracts": 3,
      "pnl": 48.78,
      "balance": 10643.4,
      "ml_confidence": 0.7134,
      "ml_active": true,
      "or_breakout": 1.0,
      "mom_30m": 0.3526
    },
    {
      "date": "2023-10-26",
      "direction": "LONG",
      "entry_price": 4186.5,
      "exit_price": 4164.25,
      "exit_type": "SL",
      "sl_points": 22.0,
      "atr": 59.0357,
      "contracts": 3,
      "pnl": -337.47,
      "balance": 10305.93,
      "ml_confidence": 0.6462,
      "ml_active": true,
      "or_breakout": 0.0,
      "mom_30m": 0.0932
    },
    {
      "date": "2023-11-02",
      "direction": "LONG",
      "entry_price": 4312.25,
      "exit_price": 4332.0,
      "exit_type": "EOD",
      "sl_points": 22.0,
      "atr": 60.3929,
      "contracts": 3,
      "pnl": 292.53,
      "balance": 10598.46,
      "ml_confidence": 0.731,
      "ml_active": true,
      "or_breakout": 1.0,
      "mom_30m": 0.12
    },
    {
      "date": "2024-01-08",
      "direction": "LONG",
      "entry_price": 4756.5,
      "exit_price": 4792.0,
      "exit_type": "EOD",
      "sl_points": 22.0,
      "atr": 44.5893,
      "contracts": 3,
      "pnl": 528.78,
      "balance": 11127.24,
      "ml_confidence": 0.6934,
      "ml_active": true,
      "or_breakout": 1.0,
      "mom_30m": 0.1177
    },
    {
      "date": "2024-01-11",
      "direction": "SHORT",
      "entry_price": 4803.75,
      "exit_price": 4783.1071,
      "exit_type": "SL",
      "sl_points": 22.0,
      "atr": 40.4286,
      "contracts": 4,
      "pnl": 407.9,
      "balance": 11535.13,
      "ml_confidence": 0.7902,
      "ml_active": true,
      "or_breakout": -1.0,
      "mom_30m": -0.1917
    },
    {
      "date": "2024-01-16",
      "direction": "LONG",
      "entry_price": 4811.25,
      "exit_price": 4789.0,
      "exit_type": "SL",
      "sl_points": 22.0,
      "atr": 37.8214,
      "contracts": 3,
      "pnl": -337.47,
      "balance": 11197.66,
      "ml_confidence": 0.5885,
      "ml_active": true,
      "or_breakout": 1.0,
      "mom_30m": 0.4561
    },
    {
      "date": "2024-01-29",
      "direction": "SHORT",
      "entry_price": 4919.25,
      "exit_price": 4941.5,
      "exit_type": "SL",
      "sl_points": 22.0,
      "atr": 37.5714,
      "contracts": 3,
      "pnl": -337.47,
      "balance": 10860.19,
      "ml_confidence": 0.5423,
      "ml_active": true,
      "or_breakout": 0.0,
      "mom_30m": -0.0532
    },
    {
      "date": "2024-02-01",
      "direction": "LONG",
      "entry_price": 4898.25,
      "exit_price": 4876.0,
      "exit_type": "SL",
      "sl_points": 22.0,
      "atr": 39.5,
      "contracts": 2,
      "pnl": -224.98,
      "balance": 10635.21,
      "ml_confidence": 0.6053,
      "ml_active": true,
      "or_breakout": 1.0,
      "mom_30m": 0.4114
    },
    {
      "date": "2024-02-12",
      "direction": "LONG",
      "entry_price": 5045.75,
      "exit_price": 5056.3393,
      "exit_type": "SL",
      "sl_points": 22.0,
      "atr": 39.6429,
      "contracts": 3,
      "pnl": 155.12,
      "balance": 10790.33,
      "ml_confidence": 0.7428,
      "ml_active": true,
      "or_breakout": 0.0,
      "mom_30m": 0.0252
    },
    {
      "date": "2024-02-13",
      "direction": "LONG",
      "entry_price": 4979.25,
      "exit_price": 4957.0,
      "exit_type": "SL",
      "sl_points": 22.0,
      "atr": 44.3929,
      "contracts": 3,
      "pnl": -337.47,
      "balance": 10452.86,
      "ml_confidence": 0.8578,
      "ml_active": true,
      "or_breakout": 0.0,
      "mom_30m": 0.2703
    },
    {
      "date": "2024-02-22",
      "direction": "LONG",
      "entry_price": 5076.75,
      "exit_price": 5096.1652,
      "exit_type": "SL",
      "sl_points": 22.0,
      "atr": 45.3393,
      "contracts": 2,
      "pnl": 191.67,
      "balance": 10644.53,
      "ml_confidence": 0.5579,
      "ml_active": true,
      "or_breakout": 0.0,
      "mom_30m": 0.0937
    },
    {
      "date": "2024-02-29",
      "direction": "SHORT",
      "entry_price": 5094.5,
      "exit_price": 5081.4375,
      "exit_type": "SL",
      "sl_points": 22.0,
      "atr": 44.75,
      "contracts": 2,
      "pnl": 128.15,
      "balance": 10772.68,
      "ml_confidence": 0.5736,
      "ml_active": true,
      "or_breakout": -1.0,
      "mom_30m": -0.1899
    },
    {
      "date": "2024-03-08",
      "direction": "LONG",
      "entry_price": 5189.75,
      "exit_price": 5167.5,
      "exit_type": "SL",
      "sl_points": 22.0,
      "atr": 48.875,
      "contracts": 3,
      "pnl": -337.47,
      "balance": 10435.21,
      "ml_confidence": 0.7576,
      "ml_active": true,
      "or_breakout": 1.0,
      "mom_30m": 0.0102
    },
    {
      "date": "2024-03-12",
      "direction": "LONG",
      "entry_price": 5163.5,
      "exit_price": 5178.75,
      "exit_type": "EOD",
      "sl_points": 22.0,
      "atr": 49.2679,
      "contracts": 3,
      "pnl": 225.03,
      "balance": 10660.24,
      "ml_confidence": 0.6506,
      "ml_active": true,
      "or_breakout": 1.0,
      "mom_30m": 0.3907
    },
    {
      "date": "2024-03-20",
      "direction": "LONG",
      "entry_price": 5247.5,
      "exit_price": 5247.25,
      "exit_type": "SL",
      "sl_points": 22.0,
      "atr": 53.2143,
      "contracts": 3,
      "pnl": -7.47,
      "balance": 10652.77,
      "ml_confidence": 0.7452,
      "ml_active": true,
      "or_breakout": 1.0,
      "mom_30m": 0.1644
    },
    {
      "date": "2024-04-08",
      "direction": "LONG",
      "entry_price": 5264.5,
      "exit_price": 5260.5,
      "exit_type": "EOD",
      "sl_points": 22.0,
      "atr": 43.6071,
      "contracts": 3,
      "pnl": -63.72,
      "balance": 10589.05,
      "ml_confidence": 0.725,
      "ml_active": true,
      "or_breakout": 1.0,
      "mom_30m": 0.2293
    },
    {
      "date": "2024-04-09",
      "direction": "SHORT",
      "entry_price": 5233.75,
      "exit_price": 5220.192,
      "exit_type": "SL",
      "sl_points": 22.0,
      "atr": 44.7679,
      "contracts": 2,
      "pnl": 133.1,
      "balance": 10722.15,
      "ml_confidence": 0.5599,
      "ml_active": true,
      "or_breakout": -1.0,
      "mom_30m": -0.4914
    },
    {
      "date": "2024-04-11",
      "direction": "SHORT",
      "entry_price": 5189.0,
      "exit_price": 5211.25,
      "exit_type": "SL",
      "sl_points": 22.0,
      "atr": 48.9107,
      "contracts": 3,
      "pnl": -337.47,
      "balance": 10384.68,
      "ml_confidence": 0.6981,
      "ml_active": true,
      "or_breakout": -1.0,
      "mom_30m": -0.2505
    },
    {
      "date": "2024-04-12",
      "direction": "SHORT",
      "entry_price": 5199.5,
      "exit_price": 5199.75,
      "exit_type": "SL",
      "sl_points": 22.0,
      "atr": 54.3214,
      "contracts": 2,
      "pnl": -4.98,
      "balance": 10379.7,
      "ml_confidence": 0.5347,
      "ml_active": true,
      "or_breakout": -1.0,
      "mom_30m": -0.2025
    },
    {
      "date": "2024-04-15",
      "direction": "SHORT",
      "entry_price": 5186.0,
      "exit_price": 5131.25,
      "exit_type": "TP",
      "sl_points": 22.0,
      "atr": 61.5893,
      "contracts": 3,
      "pnl": 817.53,
      "balance": 11197.23,
      "ml_confidence": 0.7561,
      "ml_active": true,
      "or_breakout": -1.0,
      "mom_30m": -0.3694
    },
    {
      "date": "2024-04-16",
      "direction": "SHORT",
      "entry_price": 5090.0,
      "exit_price": 5112.25,
      "exit_type": "SL",
      "sl_points": 22.0,
      "atr": 62.5357,
      "contracts": 3,
      "pnl": -337.47,
      "balance": 10859.76,
      "ml_confidence": 0.6069,
      "ml_active": true,
      "or_breakout": 0.0,
      "mom_30m": -0.1439
    },
    {
      "date": "2024-04-17",
      "direction": "SHORT",
      "entry_price": 5098.5,
      "exit_price": 5063.375,
      "exit_type": "SL",
      "sl_points": 22.0,
      "atr": 64.5,
      "contracts": 2,
      "pnl": 348.77,
      "balance": 11208.53,
      "ml_confidence": 0.5334,
      "ml_active": true,
      "or_breakout": -1.0,
      "mom_30m": -0.093
    },
    {
      "date": "2024-04-18",
      "direction": "LONG",
      "entry_price": 5077.0,
      "exit_price": 5076.75,
      "exit_type": "SL",
      "sl_points": 22.0,
      "atr": 67.3036,
      "contracts": 4,
      "pnl": -9.96,
      "balance": 11198.57,
      "ml_confidence": 0.6664,
      "ml_active": true,
      "or_breakout": 1.0,
      "mom_30m": 0.2043
    },
    {
      "date": "2024-04-19",
      "direction": "SHORT",
      "entry_price": 5038.0,
      "exit_price": 5020.3973,
      "exit_type": "SL",
      "sl_points": 22.0,
      "atr": 69.5893,
      "contracts": 4,
      "pnl": 347.09,
      "balance": 11545.66,
      "ml_confidence": 0.6432,
      "ml_active": true,
      "or_breakout": -1.0,
      "mom_30m": -0.1904
    },
    {
      "date": "2024-04-23",
      "direction": "LONG",
      "entry_price": 5099.25,
      "exit_price": 5104.25,
      "exit_type": "EOD",
      "sl_points": 22.0,
      "atr": 72.8036,
      "contracts": 4,
      "pnl": 95.04,
      "balance": 11640.7,
      "ml_confidence": 0.7286,
      "ml_active": true,
      "or_breakout": 1.0,
      "mom_30m": 0.2369
    },
    {
      "date": "2024-05-01",
      "direction": "LONG",
      "entry_price": 5052.25,
      "exit_price": 5107.0,
      "exit_type": "TP",
      "sl_points": 22.0,
      "atr": 70.0536,
      "contracts": 3,
      "pnl": 817.53,
      "balance": 12458.23,
      "ml_confidence": 0.5344,
      "ml_active": true,
      "or_breakout": 0.0,
      "mom_30m": 0.0785
    },
    {
      "date": "2024-05-23",
      "direction": "SHORT",
      "entry_price": 5327.25,
      "exit_price": 5327.5,
      "exit_type": "SL",
      "sl_points": 22.0,
      "atr": 37.5536,
      "contracts": 3,
      "pnl": -7.47,
      "balance": 12450.76,
      "ml_confidence": 0.5551,
      "ml_active": true,
      "or_breakout": 0.0,
      "mom_30m": -0.0999
    },
    {
      "date": "2024-05-29",
      "direction": "LONG",
      "entry_price": 5294.25,
      "exit_price": 5293.25,
      "exit_type": "EOD",
      "sl_points": 22.0,
      "atr": 38.0357,
      "contracts": 3,
      "pnl": -18.72,
      "balance": 12432.04,
      "ml_confidence": 0.5893,
      "ml_active": true,
      "or_breakout": 1.0,
      "mom_30m": 0.1643
    },
    {
      "date": "2024-05-31",
      "direction": "SHORT",
      "entry_price": 5229.75,
      "exit_price": 5216.7232,
      "exit_type": "SL",
      "sl_points": 22.0,
      "atr": 43.8929,
      "contracts": 4,
      "pnl": 255.58,
      "balance": 12687.62,
      "ml_confidence": 0.685,
      "ml_active": true,
      "or_breakout": -1.0,
      "mom_30m": -0.4443
    },
    {
      "date": "2024-06-05",
      "direction": "LONG",
      "entry_price": 5324.0,
      "exit_price": 5358.0,
      "exit_type": "EOD",
      "sl_points": 22.0,
      "atr": 46.9107,
      "contracts": 4,
      "pnl": 675.04,
      "balance": 13362.66,
      "ml_confidence": 0.8344,
      "ml_active": true,
      "or_breakout": 0.0,
      "mom_30m": 0.1119
    },
    {
      "date": "2024-06-10",
      "direction": "LONG",
      "entry_price": 5351.5,
      "exit_price": 5369.25,
      "exit_type": "EOD",
      "sl_points": 22.0,
      "atr": 49.3571,
      "contracts": 4,
      "pnl": 350.04,
      "balance": 13712.7,
      "ml_confidence": 0.6408,
      "ml_active": true,
      "or_breakout": 1.0,
      "mom_30m": 0.0962
    },
    {
      "date": "2024-08-15",
      "direction": "LONG",
      "entry_price": 5543.25,
      "exit_price": 5568.5,
      "exit_type": "EOD",
      "sl_points": 22.0,
      "atr": 108.3571,
      "contracts": 3,
      "pnl": 375.03,
      "balance": 14087.73,
      "ml_confidence": 0.6104,
      "ml_active": true,
      "or_breakout": 1.0,
      "mom_30m": 0.0485
    },
    {
      "date": "2024-08-21",
      "direction": "SHORT",
      "entry_price": 5636.75,
      "exit_price": 5637.0,
      "exit_type": "SL",
      "sl_points": 22.0,
      "atr": 91.7857,
      "contracts": 4,
      "pnl": -9.96,
      "balance": 14077.77,
      "ml_confidence": 0.7752,
      "ml_active": true,
      "or_breakout": 0.0,
      "mom_30m": -0.03
    },
    {
      "date": "2024-08-23",
      "direction": "LONG",
      "entry_price": 5658.5,
      "exit_price": 5636.25,
      "exit_type": "SL",
      "sl_points": 22.0,
      "atr": 75.5714,
      "contracts": 4,
      "pnl": -449.96,
      "balance": 13627.81,
      "ml_confidence": 0.7239,
      "ml_active": true,
      "or_breakout": 1.0,
      "mom_30m": 0.2382
    },
    {
      "date": "2024-08-27",
      "direction": "LONG",
      "entry_price": 5641.5,
      "exit_price": 5642.5,
      "exit_type": "EOD",
      "sl_points": 22.0,
      "atr": 63.2321,
      "contracts": 4,
      "pnl": 15.04,
      "balance": 13642.85,
      "ml_confidence": 0.6308,
      "ml_active": true,
      "or_breakout": 1.0,
      "mom_30m": 0.2254
    },
    {
      "date": "2024-08-30",
      "direction": "SHORT",
      "entry_price": 5636.75,
      "exit_price": 5619.7321,
      "exit_type": "SL",
      "sl_points": 22.0,
      "atr": 60.9286,
      "contracts": 3,
      "pnl": 251.55,
      "balance": 13894.4,
      "ml_confidence": 0.5636,
      "ml_active": true,
      "or_breakout": 0.0,
      "mom_30m": -0.1108
    },
    {
      "date": "2024-09-02",
      "direction": "SHORT",
      "entry_price": 5656.75,
      "exit_price": 5665.5,
      "exit_type": "END",
      "sl_points": 22.0,
      "atr": 55.5893,
      "contracts": 4,
      "pnl": -179.96,
      "balance": 13714.44,
      "ml_confidence": 0.7,
      "ml_active": true,
      "or_breakout": 0.0,
      "mom_30m": -0.009
    },
    {
      "date": "2024-09-05",
      "direction": "LONG",
      "entry_price": 5554.25,
      "exit_price": 5532.0,
      "exit_type": "SL",
      "sl_points": 22.0,
      "atr": 61.3929,
      "contracts": 3,
      "pnl": -337.47,
      "balance": 13376.97,
      "ml_confidence": 0.5583,
      "ml_active": true,
      "or_breakout": 1.0,
      "mom_30m": 0.114
    },
    {
      "date": "2024-09-06",
      "direction": "SHORT",
      "entry_price": 5463.5,
      "exit_price": 5463.75,
      "exit_type": "SL",
      "sl_points": 22.0,
      "atr": 66.0357,
      "contracts": 4,
      "pnl": -9.96,
      "balance": 13367.01,
      "ml_confidence": 0.706,
      "ml_active": true,
      "or_breakout": -1.0,
      "mom_30m": -0.4429
    },
    {
      "date": "2024-09-11",
      "direction": "SHORT",
      "entry_price": 5419.75,
      "exit_price": 5442.0,
      "exit_type": "SL",
      "sl_points": 22.0,
      "atr": 74.7143,
      "contracts": 3,
      "pnl": -337.47,
      "balance": 13029.54,
      "ml_confidence": 0.6178,
      "ml_active": true,
      "or_breakout": -1.0,
      "mom_30m": -0.425
    },
    {
      "date": "2024-09-18",
      "direction": "SHORT",
      "entry_price": 5636.25,
      "exit_price": 5658.5,
      "exit_type": "SL",
      "sl_points": 22.0,
      "atr": 74.0357,
      "contracts": 4,
      "pnl": -449.96,
      "balance": 12579.58,
      "ml_confidence": 0.6651,
      "ml_active": true,
      "or_breakout": 0.0,
      "mom_30m": -0.027
    },
    {
      "date": "2024-09-19",
      "direction": "LONG",
      "entry_price": 5723.25,
      "exit_price": 5717.5,
      "exit_type": "EOD",
      "sl_points": 22.0,
      "atr": 77.2857,
      "contracts": 4,
      "pnl": -119.96,
      "balance": 12459.62,
      "ml_confidence": 0.644,
      "ml_active": true,
      "or_breakout": 1.0,
      "mom_30m": 0.2232
    },
    {
      "date": "2024-09-26",
      "direction": "SHORT",
      "entry_price": 5805.75,
      "exit_price": 5806.0,
      "exit_type": "SL",
      "sl_points": 22.0,
      "atr": 70.6071,
      "contracts": 3,
      "pnl": -7.47,
      "balance": 12452.15,
      "ml_confidence": 0.5789,
      "ml_active": true,
      "or_breakout": -1.0,
      "mom_30m": -0.1629
    },
    {
      "date": "2024-10-08",
      "direction": "LONG",
      "entry_price": 5780.25,
      "exit_price": 5798.75,
      "exit_type": "EOD",
      "sl_points": 22.0,
      "atr": 60.1964,
      "contracts": 3,
      "pnl": 273.78,
      "balance": 12725.93,
      "ml_confidence": 0.6132,
      "ml_active": true,
      "or_breakout": 1.0,
      "mom_30m": -0.0249
    },
    {
      "date": "2024-10-16",
      "direction": "LONG",
      "entry_price": 5874.25,
      "exit_price": 5886.5,
      "exit_type": "EOD",
      "sl_points": 22.0,
      "atr": 53.7857,
      "contracts": 3,
      "pnl": 180.03,
      "balance": 12905.96,
      "ml_confidence": 0.5436,
      "ml_active": true,
      "or_breakout": 1.0,
      "mom_30m": 0.344
    },
    {
      "date": "2024-10-18",
      "direction": "LONG",
      "entry_price": 5895.75,
      "exit_price": 5904.75,
      "exit_type": "EOD",
      "sl_points": 22.0,
      "atr": 51.3393,
      "contracts": 3,
      "pnl": 131.28,
      "balance": 13037.24,
      "ml_confidence": 0.5234,
      "ml_active": true,
      "or_breakout": 0.0,
      "mom_30m": 0.0097
    },
    {
      "date": "2024-11-26",
      "direction": "LONG",
      "entry_price": 6020.5,
      "exit_price": 6034.0,
      "exit_type": "EOD",
      "sl_points": 22.0,
      "atr": 53.6429,
      "contracts": 3,
      "pnl": 198.78,
      "balance": 13236.02,
      "ml_confidence": 0.5447,
      "ml_active": true,
      "or_breakout": 0.0,
      "mom_30m": 0.0373
    },
    {
      "date": "2024-11-28",
      "direction": "LONG",
      "entry_price": 6030.5,
      "exit_price": 6030.0,
      "exit_type": "END",
      "sl_points": 22.0,
      "atr": 50.7679,
      "contracts": 3,
      "pnl": -11.22,
      "balance": 13224.8,
      "ml_confidence": 0.5331,
      "ml_active": true,
      "or_breakout": 1.0,
      "mom_30m": 0.0345
    },
    {
      "date": "2024-12-12",
      "direction": "LONG",
      "entry_price": 6081.75,
      "exit_price": 6065.75,
      "exit_type": "EOD",
      "sl_points": 22.0,
      "atr": 33.9464,
      "contracts": 4,
      "pnl": -324.96,
      "balance": 12899.84,
      "ml_confidence": 0.7563,
      "ml_active": true,
      "or_breakout": 0.0,
      "mom_30m": 0.1473
    },
    {
      "date": "2024-12-13",
      "direction": "SHORT",
      "entry_price": 6065.5,
      "exit_price": 6052.2366,
      "exit_type": "SL",
      "sl_points": 22.0,
      "atr": 32.9464,
      "contracts": 4,
      "pnl": 260.31,
      "balance": 13160.14,
      "ml_confidence": 0.7384,
      "ml_active": true,
      "or_breakout": -1.0,
      "mom_30m": -0.2352
    },
    {
      "date": "2024-12-16",
      "direction": "LONG",
      "entry_price": 6077.75,
      "exit_price": 6087.75,
      "exit_type": "EOD",
      "sl_points": 22.0,
      "atr": 32.7143,
      "contracts": 3,
      "pnl": 146.28,
      "balance": 13306.42,
      "ml_confidence": 0.6156,
      "ml_active": true,
      "or_breakout": 1.0,
      "mom_30m": 0.0076
    },
    {
      "date": "2024-12-23",
      "direction": "SHORT",
      "entry_price": 5979.5,
      "exit_price": 6001.75,
      "exit_type": "SL",
      "sl_points": 22.0,
      "atr": 59.8393,
      "contracts": 4,
      "pnl": -449.96,
      "balance": 12856.46,
      "ml_confidence": 0.6747,
      "ml_active": true,
      "or_breakout": -1.0,
      "mom_30m": -0.1546
    },
    {
      "date": "2024-12-26",
      "direction": "LONG",
      "entry_price": 6085.5,
      "exit_price": 6098.5,
      "exit_type": "EOD",
      "sl_points": 22.0,
      "atr": 63.4286,
      "contracts": 4,
      "pnl": 255.04,
      "balance": 13111.5,
      "ml_confidence": 0.6881,
      "ml_active": true,
      "or_breakout": 0.0,
      "mom_30m": 0.0315
    },
    {
      "date": "2025-01-03",
      "direction": "LONG",
      "entry_price": 5951.25,
      "exit_price": 5987.0,
      "exit_type": "EOD",
      "sl_points": 22.0,
      "atr": 84.9107,
      "contracts": 4,
      "pnl": 710.04,
      "balance": 13821.54,
      "ml_confidence": 0.6227,
      "ml_active": true,
      "or_breakout": 0.0,
      "mom_30m": 0.0412
    },
    {
      "date": "2025-01-07",
      "direction": "SHORT",
      "entry_price": 5998.25,
      "exit_price": 5998.5,
      "exit_type": "SL",
      "sl_points": 22.0,
      "atr": 93.0357,
      "contracts": 4,
      "pnl": -9.96,
      "balance": 13811.58,
      "ml_confidence": 0.6361,
      "ml_active": true,
      "or_breakout": -1.0,
      "mom_30m": -0.223
    },
    {
      "date": "2025-01-13",
      "direction": "SHORT",
      "entry_price": 5825.75,
      "exit_price": 5848.0,
      "exit_type": "SL",
      "sl_points": 22.0,
      "atr": 89.5179,
      "contracts": 4,
      "pnl": -449.96,
      "balance": 13361.62,
      "ml_confidence": 0.7141,
      "ml_active": true,
      "or_breakout": 0.0,
      "mom_30m": -0.0977
    },
    {
      "date": "2025-01-15",
      "direction": "LONG",
      "entry_price": 5986.75,
      "exit_price": 5964.5,
      "exit_type": "SL",
      "sl_points": 22.0,
      "atr": 85.3571,
      "contracts": 3,
      "pnl": -337.47,
      "balance": 13024.15,
      "ml_confidence": 0.563,
      "ml_active": true,
      "or_breakout": 1.0,
      "mom_30m": 0.0264
    },
    {
      "date": "2025-01-17",
      "direction": "LONG",
      "entry_price": 6026.0,
      "exit_price": 6039.0,
      "exit_type": "EOD",
      "sl_points": 22.0,
      "atr": 85.5357,
      "contracts": 4,
      "pnl": 255.04,
      "balance": 13279.19,
      "ml_confidence": 0.651,
      "ml_active": true,
      "or_breakout": 0.0,
      "mom_30m": 0.0205
    },
    {
      "date": "2025-01-27",
      "direction": "LONG",
      "entry_price": 6040.75,
      "exit_price": 6018.5,
      "exit_type": "SL",
      "sl_points": 22.0,
      "atr": 71.3571,
      "contracts": 3,
      "pnl": -337.47,
      "balance": 12941.72,
      "ml_confidence": 0.5246,
      "ml_active": true,
      "or_breakout": 1.0,
      "mom_30m": 0.0631
    },
    {
      "date": "2025-01-28",
      "direction": "LONG",
      "entry_price": 6075.5,
      "exit_price": 6101.0,
      "exit_type": "EOD",
      "sl_points": 22.0,
      "atr": 69.3214,
      "contracts": 4,
      "pnl": 505.04,
      "balance": 13446.76,
      "ml_confidence": 0.8205,
      "ml_active": true,
      "or_breakout": 1.0,
      "mom_30m": 0.4688
    },
    {
      "date": "2025-02-03",
      "direction": "LONG",
      "entry_price": 6004.5,
      "exit_price": 6004.25,
      "exit_type": "SL",
      "sl_points": 22.0,
      "atr": 70.5893,
      "contracts": 4,
      "pnl": -9.96,
      "balance": 13436.8,
      "ml_confidence": 0.7082,
      "ml_active": true,
      "or_breakout": 1.0,
      "mom_30m": 0.5702
    },
    {
      "date": "2025-02-10",
      "direction": "LONG",
      "entry_price": 6090.5,
      "exit_price": 6088.0,
      "exit_type": "EOD",
      "sl_points": 22.0,
      "atr": 67.625,
      "contracts": 3,
      "pnl": -41.22,
      "balance": 13395.58,
      "ml_confidence": 0.5506,
      "ml_active": true,
      "or_breakout": 1.0,
      "mom_30m": 0.2033
    },
    {
      "date": "2025-02-11",
      "direction": "LONG",
      "entry_price": 6081.25,
      "exit_price": 6091.75,
      "exit_type": "EOD",
      "sl_points": 22.0,
      "atr": 66.6071,
      "contracts": 3,
      "pnl": 153.78,
      "balance": 13549.36,
      "ml_confidence": 0.5528,
      "ml_active": true,
      "or_breakout": 1.0,
      "mom_30m": 0.1013
    },
    {
      "date": "2025-02-17",
      "direction": "LONG",
      "entry_price": 6140.75,
      "exit_price": 6145.25,
      "exit_type": "END",
      "sl_points": 22.0,
      "atr": 57.2679,
      "contracts": 3,
      "pnl": 63.78,
      "balance": 13613.14,
      "ml_confidence": 0.5399,
      "ml_active": true,
      "or_breakout": 0.0,
      "mom_30m": 0.0437
    },
    {
      "date": "2025-03-03",
      "direction": "LONG",
      "entry_price": 5965.5,
      "exit_price": 5943.25,
      "exit_type": "SL",
      "sl_points": 22.0,
      "atr": 76.625,
      "contracts": 3,
      "pnl": -337.47,
      "balance": 13275.67,
      "ml_confidence": 0.5782,
      "ml_active": true,
      "or_breakout": 0.0,
      "mom_30m": 0.3034
    },
    {
      "date": "2025-03-12",
      "direction": "SHORT",
      "entry_price": 5600.75,
      "exit_price": 5601.0,
      "exit_type": "SL",
      "sl_points": 22.0,
      "atr": 120.2679,
      "contracts": 4,
      "pnl": -9.96,
      "balance": 13265.71,
      "ml_confidence": 0.6822,
      "ml_active": true,
      "or_breakout": 0.0,
      "mom_30m": -0.0291
    },
    {
      "date": "2025-03-14",
      "direction": "LONG",
      "entry_price": 5583.75,
      "exit_price": 5638.5,
      "exit_type": "TP",
      "sl_points": 22.0,
      "atr": 122.9107,
      "contracts": 3,
      "pnl": 817.53,
      "balance": 14083.24,
      "ml_confidence": 0.5714,
      "ml_active": true,
      "or_breakout": 0.0,
      "mom_30m": 0.0468
    },
    {
      "date": "2025-03-27",
      "direction": "LONG",
      "entry_price": 5764.25,
      "exit_price": 5742.0,
      "exit_type": "SL",
      "sl_points": 22.0,
      "atr": 101.1964,
      "contracts": 4,
      "pnl": -449.96,
      "balance": 13633.28,
      "ml_confidence": 0.6981,
      "ml_active": true,
      "or_breakout": 1.0,
      "mom_30m": 0.0543
    },
    {
      "date": "2025-04-14",
      "direction": "LONG",
      "entry_price": 5471.0,
      "exit_price": 5448.75,
      "exit_type": "SL",
      "sl_points": 22.0,
      "atr": 227.7857,
      "contracts": 3,
      "pnl": -337.47,
      "balance": 13295.81,
      "ml_confidence": 0.6194,
      "ml_active": true,
      "or_breakout": 0.0,
      "mom_30m": 0.0604
    },
    {
      "date": "2025-04-23",
      "direction": "LONG",
      "entry_price": 5488.5,
      "exit_price": 5466.25,
      "exit_type": "SL",
      "sl_points": 22.0,
      "atr": 242.5,
      "contracts": 3,
      "pnl": -337.47,
      "balance": 12958.34,
      "ml_confidence": 0.6048,
      "ml_active": true,
      "or_breakout": 0.0,
      "mom_30m": 0.0495
    },
    {
      "date": "2025-05-07",
      "direction": "LONG",
      "entry_price": 5654.75,
      "exit_price": 5632.5,
      "exit_type": "SL",
      "sl_points": 22.0,
      "atr": 106.9286,
      "contracts": 3,
      "pnl": -337.47,
      "balance": 12620.87,
      "ml_confidence": 0.59,
      "ml_active": true,
      "or_breakout": 1.0,
      "mom_30m": 0.0491
    },
    {
      "date": "2025-05-08",
      "direction": "LONG",
      "entry_price": 5681.25,
      "exit_price": 5659.0,
      "exit_type": "SL",
      "sl_points": 22.0,
      "atr": 108.1786,
      "contracts": 3,
      "pnl": -337.47,
      "balance": 12283.4,
      "ml_confidence": 0.6113,
      "ml_active": true,
      "or_breakout": 0.0,
      "mom_30m": 0.0092
    },
    {
      "date": "2025-05-29",
      "direction": "SHORT",
      "entry_price": 5924.25,
      "exit_price": 5902.7366,
      "exit_type": "SL",
      "sl_points": 22.0,
      "atr": 74.9464,
      "contracts": 3,
      "pnl": 318.98,
      "balance": 12602.39,
      "ml_confidence": 0.5911,
      "ml_active": true,
      "or_breakout": -1.0,
      "mom_30m": -0.1301
    },
    {
      "date": "2025-06-03",
      "direction": "LONG",
      "entry_price": 5958.0,
      "exit_price": 5982.5,
      "exit_type": "EOD",
      "sl_points": 22.0,
      "atr": 69.5536,
      "contracts": 3,
      "pnl": 363.78,
      "balance": 12966.17,
      "ml_confidence": 0.5864,
      "ml_active": true,
      "or_breakout": 1.0,
      "mom_30m": 0.1366
    },
    {
      "date": "2025-06-05",
      "direction": "LONG",
      "entry_price": 5979.5,
      "exit_price": 5979.25,
      "exit_type": "SL",
      "sl_points": 22.0,
      "atr": 68.9464,
      "contracts": 3,
      "pnl": -7.47,
      "balance": 12958.7,
      "ml_confidence": 0.5429,
      "ml_active": true,
      "or_breakout": 0.0,
      "mom_30m": 0.2103
    },
    {
      "date": "2025-06-06",
      "direction": "SHORT",
      "entry_price": 6007.25,
      "exit_price": 6007.5,
      "exit_type": "SL",
      "sl_points": 22.0,
      "atr": 69.0893,
      "contracts": 3,
      "pnl": -7.47,
      "balance": 12951.23,
      "ml_confidence": 0.5296,
      "ml_active": true,
      "or_breakout": 0.0,
      "mom_30m": -0.1484
    },
    {
      "date": "2025-06-16",
      "direction": "LONG",
      "entry_price": 6052.25,
      "exit_price": 6030.0,
      "exit_type": "SL",
      "sl_points": 22.0,
      "atr": 61.2321,
      "contracts": 4,
      "pnl": -449.96,
      "balance": 12501.27,
      "ml_confidence": 0.6285,
      "ml_active": true,
      "or_breakout": 1.0,
      "mom_30m": 0.147
    },
    {
      "date": "2025-06-26",
      "direction": "LONG",
      "entry_price": 6178.0,
      "exit_price": 6192.5,
      "exit_type": "EOD",
      "sl_points": 22.0,
      "atr": 64.1429,
      "contracts": 4,
      "pnl": 285.04,
      "balance": 12786.31,
      "ml_confidence": 0.8225,
      "ml_active": true,
      "or_breakout": 1.0,
      "mom_30m": 0.1052
    },
    {
      "date": "2025-06-30",
      "direction": "LONG",
      "entry_price": 6240.5,
      "exit_price": 6249.5,
      "exit_type": "EOD",
      "sl_points": 22.0,
      "atr": 63.625,
      "contracts": 4,
      "pnl": 175.04,
      "balance": 12961.35,
      "ml_confidence": 0.6935,
      "ml_active": true,
      "or_breakout": 0.0,
      "mom_30m": 0.0432
    },
    {
      "date": "2025-07-02",
      "direction": "LONG",
      "entry_price": 6259.5,
      "exit_price": 6269.75,
      "exit_type": "EOD",
      "sl_points": 22.0,
      "atr": 61.4286,
      "contracts": 4,
      "pnl": 200.04,
      "balance": 13161.39,
      "ml_confidence": 0.6632,
      "ml_active": true,
      "or_breakout": 1.0,
      "mom_30m": 0.1953
    },
    {
      "date": "2025-07-08",
      "direction": "SHORT",
      "entry_price": 6270.0,
      "exit_price": 6272.25,
      "exit_type": "EOD",
      "sl_points": 22.0,
      "atr": 56.1964,
      "contracts": 4,
      "pnl": -49.96,
      "balance": 13111.43,
      "ml_confidence": 0.6994,
      "ml_active": true,
      "or_breakout": -1.0,
      "mom_30m": -0.0979
    },
    {
      "date": "2025-07-10",
      "direction": "LONG",
      "entry_price": 6305.0,
      "exit_price": 6328.25,
      "exit_type": "EOD",
      "sl_points": 22.0,
      "atr": 54.0357,
      "contracts": 3,
      "pnl": 345.03,
      "balance": 13456.46,
      "ml_confidence": 0.5334,
      "ml_active": true,
      "or_breakout": 0.0,
      "mom_30m": 0.1342
    },
    {
      "date": "2025-08-06",
      "direction": "SHORT",
      "entry_price": 6331.25,
      "exit_price": 6353.5,
      "exit_type": "SL",
      "sl_points": 22.0,
      "atr": 55.1964,
      "contracts": 4,
      "pnl": -449.96,
      "balance": 13006.5,
      "ml_confidence": 0.6754,
      "ml_active": true,
      "or_breakout": 0.0,
      "mom_30m": -0.0996
    },
    {
      "date": "2025-08-07",
      "direction": "SHORT",
      "entry_price": 6377.25,
      "exit_price": 6358.9018,
      "exit_type": "SL",
      "sl_points": 22.0,
      "atr": 58.6071,
      "contracts": 3,
      "pnl": 271.5,
      "balance": 13278.0,
      "ml_confidence": 0.5725,
      "ml_active": true,
      "or_breakout": -1.0,
      "mom_30m": -0.5588
    },
    {
      "date": "2025-08-08",
      "direction": "LONG",
      "entry_price": 6409.0,
      "exit_price": 6413.5,
      "exit_type": "EOD",
      "sl_points": 22.0,
      "atr": 59.4821,
      "contracts": 4,
      "pnl": 85.04,
      "balance": 13363.04,
      "ml_confidence": 0.6366,
      "ml_active": true,
      "or_breakout": 1.0,
      "mom_30m": 0.1219
    },
    {
      "date": "2025-09-04",
      "direction": "LONG",
      "entry_price": 6472.75,
      "exit_price": 6499.5,
      "exit_type": "EOD",
      "sl_points": 22.0,
      "atr": 51.6786,
      "contracts": 4,
      "pnl": 530.04,
      "balance": 13893.08,
      "ml_confidence": 0.7038,
      "ml_active": true,
      "or_breakout": 0.0,
      "mom_30m": 0.0435
    },
    {
      "date": "2025-09-08",
      "direction": "LONG",
      "entry_price": 6508.25,
      "exit_price": 6494.5,
      "exit_type": "EOD",
      "sl_points": 22.0,
      "atr": 54.6429,
      "contracts": 3,
      "pnl": -209.97,
      "balance": 13683.11,
      "ml_confidence": 0.5644,
      "ml_active": true,
      "or_breakout": 0.0,
      "mom_30m": 0.1327
    },
    {
      "date": "2025-09-15",
      "direction": "LONG",
      "entry_price": 6620.75,
      "exit_price": 6612.25,
      "exit_type": "EOD",
      "sl_points": 22.0,
      "atr": 47.9643,
      "contracts": 3,
      "pnl": -131.22,
      "balance": 13551.89,
      "ml_confidence": 0.6018,
      "ml_active": true,
      "or_breakout": 1.0,
      "mom_30m": 0.0573
    },
    {
      "date": "2025-09-22",
      "direction": "LONG",
      "entry_price": 6725.0,
      "exit_price": 6755.5,
      "exit_type": "EOD",
      "sl_points": 22.0,
      "atr": 57.2143,
      "contracts": 4,
      "pnl": 605.04,
      "balance": 14156.93,
      "ml_confidence": 0.8297,
      "ml_active": true,
      "or_breakout": 1.0,
      "mom_30m": 0.1529
    },
    {
      "date": "2025-09-26",
      "direction": "SHORT",
      "entry_price": 6662.25,
      "exit_price": 6684.5,
      "exit_type": "SL",
      "sl_points": 22.0,
      "atr": 51.6964,
      "contracts": 3,
      "pnl": -337.47,
      "balance": 13819.46,
      "ml_confidence": 0.5351,
      "ml_active": true,
      "or_breakout": -1.0,
      "mom_30m": -0.7206
    },
    {
      "date": "2025-10-02",
      "direction": "SHORT",
      "entry_price": 6763.5,
      "exit_price": 6763.75,
      "exit_type": "SL",
      "sl_points": 22.0,
      "atr": 53.3036,
      "contracts": 4,
      "pnl": -9.96,
      "balance": 13809.5,
      "ml_confidence": 0.6639,
      "ml_active": true,
      "or_breakout": 0.0,
      "mom_30m": -0.0516
    },
    {
      "date": "2025-10-06",
      "direction": "LONG",
      "entry_price": 6777.5,
      "exit_price": 6788.25,
      "exit_type": "EOD",
      "sl_points": 22.0,
      "atr": 54.6964,
      "contracts": 3,
      "pnl": 157.53,
      "balance": 13967.03,
      "ml_confidence": 0.5404,
      "ml_active": true,
      "or_breakout": 0.0,
      "mom_30m": 0.064
    },
    {
      "date": "2025-10-08",
      "direction": "LONG",
      "entry_price": 6790.0,
      "exit_price": 6800.0,
      "exit_type": "EOD",
      "sl_points": 22.0,
      "atr": 54.25,
      "contracts": 4,
      "pnl": 195.04,
      "balance": 14162.07,
      "ml_confidence": 0.666,
      "ml_active": true,
      "or_breakout": 1.0,
      "mom_30m": 0.235
    },
    {
      "date": "2025-10-20",
      "direction": "LONG",
      "entry_price": 6761.75,
      "exit_price": 6776.5,
      "exit_type": "EOD",
      "sl_points": 22.0,
      "atr": 84.0,
      "contracts": 3,
      "pnl": 217.53,
      "balance": 14379.6,
      "ml_confidence": 0.5314,
      "ml_active": true,
      "or_breakout": 1.0,
      "mom_30m": 0.1369
    },
    {
      "date": "2025-10-31",
      "direction": "LONG",
      "entry_price": 6884.5,
      "exit_price": 6862.25,
      "exit_type": "SL",
      "sl_points": 22.0,
      "atr": 77.5893,
      "contracts": 4,
      "pnl": -449.96,
      "balance": 13929.64,
      "ml_confidence": 0.6224,
      "ml_active": true,
      "or_breakout": 0.0,
      "mom_30m": 0.0032
    },
    {
      "date": "2025-11-20",
      "direction": "SHORT",
      "entry_price": 6784.25,
      "exit_price": 6729.5,
      "exit_type": "TP",
      "sl_points": 22.0,
      "atr": 100.6429,
      "contracts": 4,
      "pnl": 1090.04,
      "balance": 15019.68,
      "ml_confidence": 0.8319,
      "ml_active": true,
      "or_breakout": 0.0,
      "mom_30m": -0.0199
    },
    {
      "date": "2025-11-25",
      "direction": "LONG",
      "entry_price": 6724.25,
      "exit_price": 6776.25,
      "exit_type": "EOD",
      "sl_points": 22.0,
      "atr": 111.1429,
      "contracts": 4,
      "pnl": 1035.04,
      "balance": 16054.72,
      "ml_confidence": 0.5399,
      "ml_active": true,
      "or_breakout": 0.0,
      "mom_30m": 0.0742
    },
    {
      "date": "2025-11-26",
      "direction": "LONG",
      "entry_price": 6812.5,
      "exit_price": 6841.75,
      "exit_type": "EOD",
      "sl_points": 22.0,
      "atr": 109.4107,
      "contracts": 5,
      "pnl": 725.05,
      "balance": 16779.77,
      "ml_confidence": 0.5577,
      "ml_active": true,
      "or_breakout": 0.0,
      "mom_30m": 0.1074
    },
    {
      "date": "2025-12-04",
      "direction": "LONG",
      "entry_price": 6860.25,
      "exit_price": 6838.0,
      "exit_type": "SL",
      "sl_points": 22.0,
      "atr": 85.7679,
      "contracts": 5,
      "pnl": -562.45,
      "balance": 16217.32,
      "ml_confidence": 0.5832,
      "ml_active": true,
      "or_breakout": 0.0,
      "mom_30m": 0.0612
    },
    {
      "date": "2025-12-16",
      "direction": "SHORT",
      "entry_price": 6790.0,
      "exit_price": 6774.942,
      "exit_type": "SL",
      "sl_points": 22.0,
      "atr": 51.7679,
      "contracts": 5,
      "pnl": 370.25,
      "balance": 16587.57,
      "ml_confidence": 0.5545,
      "ml_active": true,
      "or_breakout": 0.0,
      "mom_30m": -0.5795
    },
    {
      "date": "2026-01-09",
      "direction": "LONG",
      "entry_price": 6995.0,
      "exit_price": 7014.5,
      "exit_type": "EOD",
      "sl_points": 22.0,
      "atr": 57.3393,
      "contracts": 5,
      "pnl": 481.3,
      "balance": 17068.87,
      "ml_confidence": 0.6848,
      "ml_active": true,
      "or_breakout": 1.0,
      "mom_30m": 0.3314
    },
    {
      "date": "2026-02-24",
      "direction": "LONG",
      "entry_price": 6893.75,
      "exit_price": 6895.5,
      "exit_type": "EOD",
      "sl_points": 22.0,
      "atr": 85.0893,
      "contracts": 5,
      "pnl": 37.55,
      "balance": 17106.42,
      "ml_confidence": 0.6812,
      "ml_active": true,
      "or_breakout": 1.0,
      "mom_30m": 0.4936
    },
    {
      "date": "2026-03-04",
      "direction": "LONG",
      "entry_price": 6880.5,
      "exit_price": 6884.75,
      "exit_type": "EOD",
      "sl_points": 22.0,
      "atr": 83.2857,
      "contracts": 5,
      "pnl": 100.05,
      "balance": 17206.47,
      "ml_confidence": 0.5668,
      "ml_active": true,
      "or_breakout": 1.0,
      "mom_30m": 0.4262
    },
    {
      "date": "2026-04-14",
      "direction": "LONG",
      "entry_price": 6971.75,
      "exit_price": 7004.0,
      "exit_type": "EOD",
      "sl_points": 22.0,
      "atr": 103.9286,
      "contracts": 5,
      "pnl": 800.05,
      "balance": 18006.52,
      "ml_confidence": 0.5536,
      "ml_active": true,
      "or_breakout": 1.0,
      "mom_30m": 0.1299
    },
    {
      "date": "2026-05-20",
      "direction": "LONG",
      "entry_price": 7424.0,
      "exit_price": 7423.75,
      "exit_type": "SL",
      "sl_points": 22.0,
      "atr": 75.5357,
      "contracts": 5,
      "pnl": -12.45,
      "balance": 17994.07,
      "ml_confidence": 0.5651,
      "ml_active": true,
      "or_breakout": 1.0,
      "mom_30m": 0.3508
    },
    {
      "date": "2026-05-21",
      "direction": "SHORT",
      "entry_price": 7426.75,
      "exit_price": 7449.0,
      "exit_type": "SL",
      "sl_points": 22.0,
      "atr": 76.7143,
      "contracts": 4,
      "pnl": -449.96,
      "balance": 17544.11,
      "ml_confidence": 0.531,
      "ml_active": true,
      "or_breakout": 0.0,
      "mom_30m": -0.1206
    }
  ]
}